clay_streamlit_one/__init__.py
clay_streamlit_one/app_page.py
clay_streamlit_one/clay_streamlit_app.py
clay_streamlit_one-0.2.12.dist-info/licenses/LICENSE
clay_streamlit_one-0.2.12.dist-info/METADATA
clay_streamlit_one-0.2.12.dist-info/WHEEL
clay_streamlit_one-0.2.12.dist-info/top_level.txt
clay_streamlit_one-0.2.12.dist-info/RECORD
