Metadata-Version: 2.4
Name: clay_streamlit_one
Version: 0.2.12
Summary: A minimal streamlit app framework
Author-email: "Ariel E." <ariel@claysciences.com>
License: MIT
Project-URL: Homepage, https://github.com/claysciences/clay_streamlit_one
Classifier: Programming Language :: Python :: 3
Classifier: License :: OSI Approved :: MIT License
Classifier: Operating System :: OS Independent
Requires-Python: >=3.7
License-File: LICENSE
Requires-Dist: streamlit>=1.23
Requires-Dist: loguru
Provides-Extra: dev
Requires-Dist: bumpver; extra == "dev"
Dynamic: license-file
